pz_fileio/File.py
pz_fileio/__init__.py
pz_fileio-1.0.1.dist-info/METADATA
pz_fileio-1.0.1.dist-info/WHEEL
pz_fileio-1.0.1.dist-info/licenses/LICENSE
pz_fileio-1.0.1.dist-info/RECORD
