Metadata-Version: 2.4
Name: pz-fileio
Version: 1.0.1
Summary: Lightweight, object-oriented utility library for convenient file management in Python.
Project-URL: Homepage, https://github.com/poziel/fileio
Project-URL: Issues, https://github.com/poziel/fileio
Author-email: Alexandre Sauvé <alexandre.sauve.dev@gmail.com>
License-File: LICENSE
Classifier: License :: OSI Approved :: MIT License
Classifier: Operating System :: OS Independent
Classifier: Programming Language :: Python :: 3
Requires-Python: >=3.0
